datar_numpy/__init__.py
datar_numpy/api/__init__.py
datar_numpy/api/arithm.py
datar_numpy/api/asis.py
datar_numpy/api/bessel.py
datar_numpy/api/complex.py
datar_numpy/api/constants.py
datar_numpy/api/cum.py
datar_numpy/api/date.py
datar_numpy/api/random.py
datar_numpy/api/seq.py
datar_numpy/api/sets.py
datar_numpy/api/special.py
datar_numpy/api/string.py
datar_numpy/api/trig.py
datar_numpy/api/which.py
datar_numpy/plugin.py
datar_numpy/utils.py
datar_numpy/version.py
datar_numpy-0.3.6.dist-info/LICENSE
datar_numpy-0.3.6.dist-info/METADATA
datar_numpy-0.3.6.dist-info/WHEEL
datar_numpy-0.3.6.dist-info/entry_points.txt
datar_numpy-0.3.6.dist-info/RECORD
