Metadata-Version: 2.3
Name: datar-numpy
Version: 0.3.6
Summary: The numpy backend for datar
License: MIT
Author: pwwang
Author-email: pwwang@pwwang.com
Requires-Python: >=3.9,<4.0
Classifier: License :: OSI Approved :: MIT License
Classifier: Programming Language :: Python :: 3
Classifier: Programming Language :: Python :: 3.9
Classifier: Programming Language :: Python :: 3.10
Classifier: Programming Language :: Python :: 3.11
Classifier: Programming Language :: Python :: 3.12
Classifier: Programming Language :: Python :: 3.13
Provides-Extra: all
Requires-Dist: datar (>=0.15.9,<0.16.0)
Requires-Dist: numpy (>=2,<3)
Requires-Dist: scipy (>=1.8,<2.0) ; extra == "all"
Requires-Dist: wcwidth (>=0.2,<0.3) ; extra == "all"
